{
    "id": 122739,
    "type": "manga",
    "title": "Neko to Kiss",
    "url": "https://myanimelist.net/manga/129280/Neko_to_Kiss",
    "total": 25,
    "image": "https://cdn.myanimelist.net/images/manga/1/249828.jpg",
    "Sites": {
        "Mangadex": {
            "e6477b27-6c4b-410f-9a29-fa60be616446": {
                "identifier": "e6477b27-6c4b-410f-9a29-fa60be616446",
                "image": "https://uploads.mangadex.org/covers/e6477b27-6c4b-410f-9a29-fa60be616446/87d6aa90-b4a2-492d-a614-83f80bafb8fa.jpg",
                "malId": 129280,
                "aniId": 122739,
                "page": "Mangadex",
                "title": "Neko to Kiss",
                "type": "manga",
                "url": "https://mangadex.org/title/e6477b27-6c4b-410f-9a29-fa60be616446"
            }
        },
        "MangaFox": {
            "neko_to_kiss": {
                "identifier": "neko_to_kiss",
                "image": "https://fmcdn.mfcdn.net/store/manga/36870/cover.jpg",
                "malId": 129280,
                "aniId": 122739,
                "page": "MangaFox",
                "title": "Neko to Kiss",
                "type": "manga",
                "url": "https://fanfox.net/manga/neko_to_kiss/"
            }
        },
        "MangaNato": {
            "manga-jm986621": {
                "identifier": "manga-jm986621",
                "image": "https://avt.mkklcdnv6temp.com/14/c/22-1600311070.jpg",
                "malId": 129280,
                "aniId": 122739,
                "page": "MangaNato",
                "title": "Cat And A Kiss",
                "type": "manga",
                "url": "https://chapmanganato.com/manga-jm986621"
            }
        },
        "MangaSee": {
            "a-kiss-with-a-cat": {
                "identifier": "a-kiss-with-a-cat",
                "image": "https://temp.compsci88.com/cover/A-Kiss-with-a-Cat.jpg",
                "malId": 129280,
                "aniId": 122739,
                "page": "MangaSee",
                "title": "A Kiss with a Cat",
                "type": "manga",
                "url": "https://mangasee123.com/manga/A-Kiss-with-a-Cat"
            }
        },
        "MangaFire": {
            "neko-to-kiss.pjkp6": {
                "identifier": "neko-to-kiss.pjkp6",
                "image": "https://static.mangafire.to/3b2d5/i/c/cf/cf1efb06f0ae3699edbfbdd29dae53cd.jpg",
                "malId": 129280,
                "aniId": 122739,
                "page": "MangaFire",
                "title": "A Kiss with a Cat",
                "type": "manga",
                "url": "https://mangafire.to/manga/neko-to-kiss.pjkp6/"
            }
        },
        "Weebcentral": {
            "01j76xyfc2vcj2pkehdzefxfhr": {
                "identifier": "01j76xyfc2vcj2pkehdzefxfhr",
                "image": "https://temp.compsci88.com/cover/fallback/01J76XYFC2VCJ2PKEHDZEFXFHR.jpg",
                "malId": 129280,
                "aniId": 122739,
                "page": "Weebcentral",
                "title": "A Kiss with a Cat",
                "type": "manga",
                "url": "https://weebcentral.com/series/01J76XYFC2VCJ2PKEHDZEFXFHR"
            }
        },
        "Comick": {
            "NSLM8KSO": {
                "identifier": "NSLM8KSO",
                "malId": 129280,
                "type": "manga",
                "page": "Comick",
                "title": "Neko to Kiss",
                "url": "https://comick.io/comic/cat-and-a-kiss",
                "aniId": 122739
            }
        },
        "MangaReader": {
            "3610": {
                "identifier": "3610",
                "malId": 129280,
                "type": "manga",
                "page": "MangaReader",
                "title": "Neko to Kiss",
                "url": "https://mangareader.to/cat-and-a-kiss-3610",
                "aniId": 122739
            }
        }
    },
    "malId": 129280
}