{
    "id": 132820,
    "type": "manga",
    "title": "Dear X",
    "url": "https://myanimelist.net/manga/147468/Dear_X",
    "total": 63,
    "image": "https://cdn.myanimelist.net/images/manga/3/262273.jpg",
    "Sites": {
        "Mangadex": {
            "8ac40b72-01ba-4ac4-8341-349c828d60f7": {
                "identifier": "8ac40b72-01ba-4ac4-8341-349c828d60f7",
                "image": "https://uploads.mangadex.org/covers/8ac40b72-01ba-4ac4-8341-349c828d60f7/6a06189c-dcd8-4b18-8012-247abb6bea0f.jpg",
                "malId": 147468,
                "aniId": 132820,
                "page": "Mangadex",
                "title": "Dear X",
                "type": "manga",
                "url": "https://mangadex.org/title/8ac40b72-01ba-4ac4-8341-349c828d60f7"
            }
        },
        "MangaFire": {
            "dear-x.3rnpr": {
                "identifier": "dear-x.3rnpr",
                "image": "https://static.bunnycdn.ru/i/cache/images/c/c6/c623dd626beedfbceed4b97e885533be.jpg",
                "malId": 147468,
                "aniId": 132820,
                "page": "MangaFire",
                "title": "Dear X",
                "type": "manga",
                "url": "https://mangafire.to/manga/dear-x.3rnpr/"
            }
        },
        "Comick": {
            "mef33OLj": {
                "identifier": "mef33OLj",
                "malId": 147468,
                "type": "manga",
                "page": "Comick",
                "title": "Dear X",
                "url": "https://comick.cc/comic/01-dear-x",
                "aniId": 132820
            }
        }
    },
    "malId": 147468
}