{
    "id": 48888,
    "type": "manga",
    "title": "Ring x Mama",
    "url": "https://myanimelist.net/manga/18888/Ring_x_Mama",
    "total": 45,
    "image": "https://cdn.myanimelist.net/images/manga/2/55503.jpg",
    "Sites": {
        "Mangadex": {
            "ec3d0b3b-d338-4fb9-a4e3-f552f5d55bea": {
                "identifier": "ec3d0b3b-d338-4fb9-a4e3-f552f5d55bea",
                "image": "https://uploads.mangadex.org/covers/ec3d0b3b-d338-4fb9-a4e3-f552f5d55bea/660c62f7-ef77-4f89-b6a5-ac0d7c2350a5.jpg",
                "malId": 18888,
                "aniId": 48888,
                "page": "Mangadex",
                "title": "Rin x Mama",
                "type": "manga",
                "url": "https://mangadex.org/title/ec3d0b3b-d338-4fb9-a4e3-f552f5d55bea"
            }
        },
        "MangaFox": {
            "ring_x_mama": {
                "identifier": "ring_x_mama",
                "image": "https://fmcdn.mfcdn.net/store/manga/8529/cover.jpg",
                "malId": 18888,
                "aniId": 48888,
                "page": "MangaFox",
                "title": "Ring x Mama",
                "type": "manga",
                "url": "https://fanfox.net/manga/ring_x_mama/"
            }
        },
        "Comick": {
            "JZIdLJh1": {
                "identifier": "JZIdLJh1",
                "malId": 18888,
                "type": "manga",
                "page": "Comick",
                "title": "Rin x Mama",
                "url": "https://comick.io/comic/rin-x-mama",
                "aniId": 48888
            }
        }
    },
    "malId": 18888
}