{
    "id": 54932,
    "type": "manga",
    "title": "Shippuudotou no Manken-bu!!",
    "url": "https://myanimelist.net/manga/24932/Shippuudotou_no_Manken-bu",
    "image": "https://cdn.myanimelist.net/images/manga/1/40111.jpg",
    "Sites": {
        "Mangadex": {
            "9bd4eed2-d585-4f20-97be-82a63998181e": {
                "identifier": "9bd4eed2-d585-4f20-97be-82a63998181e",
                "image": "https://uploads.mangadex.org/covers/9bd4eed2-d585-4f20-97be-82a63998181e/fb120fc5-2377-4fca-aa2a-1fbe7245a976.jpg",
                "malId": 24932,
                "aniId": 54932,
                "page": "Mangadex",
                "title": "Shippuudotou no Mankenbu!!",
                "type": "manga",
                "url": "https://mangadex.org/title/9bd4eed2-d585-4f20-97be-82a63998181e"
            }
        }
    },
    "malId": 24932
}