{
    "id": 65197,
    "type": "manga",
    "title": "Boku no Chopin",
    "url": "https://myanimelist.net/manga/35197/Boku_no_Chopin",
    "total": 30,
    "image": "https://cdn.myanimelist.net/images/manga/3/124925.jpg",
    "Sites": {
        "Mangadex": {
            "bdb5580b-471a-4f3b-b6de-5e743849cf1d": {
                "identifier": "bdb5580b-471a-4f3b-b6de-5e743849cf1d",
                "image": "https://uploads.mangadex.org/covers/bdb5580b-471a-4f3b-b6de-5e743849cf1d/4e4f019e-a1fc-48d0-81d5-10092f266a4c.jpg",
                "malId": 35197,
                "aniId": 65197,
                "page": "Mangadex",
                "title": "Boku no Chopin",
                "type": "manga",
                "url": "https://mangadex.org/title/bdb5580b-471a-4f3b-b6de-5e743849cf1d"
            }
        },
        "MangaSee": {
            "boku-no-chopin": {
                "identifier": "boku-no-chopin",
                "image": "https://temp.compsci88.com/cover/Boku-No-Chopin.jpg",
                "malId": 35197,
                "aniId": 65197,
                "page": "MangaSee",
                "title": "Boku no Chopin",
                "type": "manga",
                "url": "https://mangasee123.com/manga/Boku-No-Chopin"
            }
        },
        "MangaFire": {
            "boku-no-chopin.km09": {
                "identifier": "boku-no-chopin.km09",
                "image": "https://static.mangafire.to/3b2d5/i/9/9a/9ad93bf8235dd2f2f946090ba9560b13.jpg",
                "malId": 35197,
                "aniId": 65197,
                "page": "MangaFire",
                "title": "Boku no Chopin",
                "type": "manga",
                "url": "https://mangafire.to/manga/boku-no-chopin.km09/"
            }
        },
        "Weebcentral": {
            "01j76xy9vxp47j4z07nxckcn3g": {
                "identifier": "01j76xy9vxp47j4z07nxckcn3g",
                "image": "https://temp.compsci88.com/cover/fallback/01J76XY9VXP47J4Z07NXCKCN3G.jpg",
                "malId": 35197,
                "aniId": 65197,
                "page": "Weebcentral",
                "title": "Boku no Chopin",
                "type": "manga",
                "url": "https://weebcentral.com/series/01J76XY9VXP47J4Z07NXCKCN3G"
            }
        },
        "Comick": {
            "JZmP5GXP": {
                "identifier": "JZmP5GXP",
                "malId": 35197,
                "type": "manga",
                "page": "Comick",
                "title": "Boku no Chopin",
                "url": "https://comick.io/comic/boku-no-chopin",
                "aniId": 65197
            }
        }
    },
    "malId": 35197
}