{
    "id": 65831,
    "type": "manga",
    "title": "M Haha Musume Choukyou Nikki",
    "url": "https://myanimelist.net/manga/35831/M_Haha_Musume_Choukyou_Nikki",
    "total": 9,
    "image": "https://cdn.myanimelist.net/images/manga/3/64897.jpg",
    "Sites": {
        "Mangadex": {
            "97de94f4-d275-4a2f-b7f8-c6157abf5319": {
                "identifier": "97de94f4-d275-4a2f-b7f8-c6157abf5319",
                "image": "https://uploads.mangadex.org/covers/97de94f4-d275-4a2f-b7f8-c6157abf5319/2b0f896b-ea34-4257-b338-c0291f48d0fd.jpg",
                "malId": 35831,
                "aniId": 65831,
                "page": "Mangadex",
                "title": "M Haha Musume Choukyou Nikki",
                "type": "manga",
                "url": "https://mangadex.org/title/97de94f4-d275-4a2f-b7f8-c6157abf5319"
            }
        },
        "Comick": {
            "C94rd1dT": {
                "identifier": "C94rd1dT",
                "malId": 35831,
                "type": "manga",
                "page": "Comick",
                "title": "M Haha Musume Choukyou Nikki",
                "url": "https://comick.io/comic/m-haha-musume-choukyou-nikki",
                "aniId": 65831
            }
        }
    },
    "malId": 35831
}