{
    "id": 96015,
    "type": "manga",
    "title": "Lady & Oldman",
    "url": "https://myanimelist.net/manga/93087/Lady___Oldman",
    "total": 47,
    "image": "https://cdn.myanimelist.net/images/manga/3/180386.jpg",
    "Sites": {
        "Mangadex": {
            "8b61fe01-6818-41ca-9df0-ad85792cee9b": {
                "identifier": "8b61fe01-6818-41ca-9df0-ad85792cee9b",
                "image": "https://uploads.mangadex.org/covers/8b61fe01-6818-41ca-9df0-ad85792cee9b/5a0bb528-2256-42e4-bdae-384b06ca8388.jpg",
                "malId": 93087,
                "aniId": 96015,
                "page": "Mangadex",
                "title": "Lady & Oldman",
                "type": "manga",
                "url": "https://mangadex.org/title/8b61fe01-6818-41ca-9df0-ad85792cee9b"
            }
        },
        "MangaNato": {
            "manga-dz980982": {
                "identifier": "manga-dz980982",
                "image": "https://avt.mkklcdnv6temp.com/48/m/17-1583497014.jpg",
                "malId": 93087,
                "aniId": 96015,
                "page": "MangaNato",
                "title": "Lady And Oldman",
                "type": "manga",
                "url": "https://chapmanganato.com/manga-dz980982"
            }
        },
        "MangaFire": {
            "lady-oldman.7jr1y": {
                "identifier": "lady-oldman.7jr1y",
                "image": "https://static.mangafire.to/3b2d5/i/c/c0/c09c0fec4fbbf8fff74f6f9a17ab7d62.jpg",
                "malId": 93087,
                "aniId": 96015,
                "page": "MangaFire",
                "title": "Lady & Oldman",
                "type": "manga",
                "url": "https://mangafire.to/manga/lady-oldman.7jr1y/"
            }
        },
        "Comick": {
            "Pxh4Hqnl": {
                "identifier": "Pxh4Hqnl",
                "malId": 93087,
                "type": "manga",
                "page": "Comick",
                "title": "Lady & Oldman",
                "url": "https://comick.io/comic/lady-and-oldman",
                "aniId": 96015
            }
        },
        "MangaReader": {
            "18278": {
                "identifier": "18278",
                "malId": 93087,
                "type": "manga",
                "page": "MangaReader",
                "title": "Lady & Oldman",
                "url": "https://mangareader.to/lady-and-oldman-18278",
                "aniId": 96015
            }
        }
    },
    "malId": 93087
}