{
    "id": 107617,
    "type": "anime",
    "title": "Ling Feng Zhe",
    "url": "https://myanimelist.net/anime/39022/Ling_Feng_Zhe",
    "total": 7,
    "image": "https://cdn.myanimelist.net/images/anime/1641/136376.jpg",
    "anidbId": 14646,
    "Sites": {
        "Gogoanime": {
            "the-leader": {
                "identifier": "the-leader",
                "image": "https://gogocdn.net/cover/the-leader.png",
                "malId": 39022,
                "aniId": 107617,
                "page": "Gogoanime",
                "title": "The Leader ",
                "type": "anime",
                "url": "https://anitaku.bz/category/the-leader"
            }
        },
        "animepahe": {
            "4608": {
                "identifier": "4608",
                "malId": 39022,
                "type": "anime",
                "page": "animepahe",
                "title": "The Leader",
                "url": "https://animepahe.ru/a/4608",
                "aniId": 107617
            }
        }
    },
    "malId": 39022
}