{
    "id": 114233,
    "type": "anime",
    "title": "Gundam Build Divers Re:Rise 2nd Season",
    "url": "https://myanimelist.net/anime/40942/Gundam_Build_Divers_Re_Rise_2nd_Season",
    "total": 13,
    "image": "https://cdn.myanimelist.net/images/anime/1962/105909.jpg",
    "anidbId": 15333,
    "Sites": {
        "Gogoanime": {
            "gundam-build-divers-rerise-2nd-season": {
                "identifier": "gundam-build-divers-rerise-2nd-season",
                "image": "https://gogocdn.net/cover/gundam-build-divers-rerise-2nd-season.png",
                "malId": 40942,
                "aniId": 114233,
                "page": "Gogoanime",
                "title": "Gundam Build Divers Re:Rise 2nd Season",
                "type": "anime",
                "url": "https://anitaku.pe/category/gundam-build-divers-rerise-2nd-season"
            },
            "gundam-build-divers-rerise-2nd-season-dub": {
                "identifier": "gundam-build-divers-rerise-2nd-season-dub",
                "image": "https://gogocdn.net/cover/gundam-build-divers-rerise-2nd-season-dub.png",
                "malId": 40942,
                "aniId": 114233,
                "page": "Gogoanime",
                "title": "Gundam Build Divers Re:Rise 2nd Season (Dub)",
                "type": "anime",
                "url": "https://anitaku.bz/category/gundam-build-divers-rerise-2nd-season-dub"
            }
        },
        "Zoro": {
            "1437": {
                "identifier": "1437",
                "image": "https://cdn.noitatnemucod.net/thumbnail/300x400/100/da46fead537e5c6e2ff11c3f3f55eec2.jpg",
                "malId": 40942,
                "aniId": 114233,
                "page": "Zoro",
                "title": "GUNDAM BUILD DIVERS Re:RISE",
                "type": "anime",
                "url": "https://hianime.to/gundam-build-divers-rerise-1437"
            }
        },
        "animepahe": {
            "3930": {
                "identifier": "3930",
                "malId": 40942,
                "type": "anime",
                "page": "animepahe",
                "title": "Gundam Build Divers Re:Rise 2nd Season",
                "url": "https://animepahe.ru/a/3930",
                "aniId": 114233
            }
        },
        "YugenAnime": {
            "5534": {
                "identifier": "5534",
                "malId": 40942,
                "type": "anime",
                "page": "YugenAnime",
                "title": "Gundam Build Divers Re:Rise 2nd Season",
                "url": "https://yugenanime.tv/anime/5534/gundam-build-divers-rerise-2nd-season/",
                "aniId": 114233
            }
        },
        "Crunchyroll": {
            "0": {
                "title": "Gundam Build Divers Re:RISE 2nd Season",
                "image": "https://s4.anilist.co/file/anilistcdn/media/anime/cover/medium/bx114233-FUlAGLqFOVrT.jpg",
                "identifier": 0,
                "url": "https://www.crunchyroll.com/gundam-build-divers",
                "type": "anime",
                "page": "Crunchyroll",
                "external": true,
                "aniId": 114233
            }
        }
    },
    "malId": 40942
}