{
    "id": 12279,
    "type": "anime",
    "title": "Kinnikuman II Sei: Muscle Ninjin Soudatsu sen! Choujin Daisensou",
    "url": "https://myanimelist.net/anime/12279/Kinnikuman_II_Sei__Muscle_Ninjin_Soudatsu_sen_Choujin_Daisensou",
    "image": "https://cdn.myanimelist.net/images/anime/1994/97587.jpg",
    "anidbId": 2132,
    "Sites": {
        "Zoro": {
            "5108": {
                "identifier": "5108",
                "image": "https://img.flawlessfiles.com/_r/300x400/100/f1/f7/f1f775a7cda15b9504d073bf1f1965b0/f1f775a7cda15b9504d073bf1f1965b0.jpg",
                "malId": 12279,
                "aniId": 12279,
                "page": "Zoro",
                "title": "Kinnikuman II Sei: Muscle Ninjin Soudatsu sen! Choujin Daisensou",
                "type": "anime",
                "url": "https://aniwatch.to/kinnikuman-ii-sei-muscle-ninjin-soudatsu-sen-choujin-daisensou-5108"
            }
        }
    },
    "malId": 12279
}