{
    "id": 128828,
    "type": "anime",
    "title": "Dolls' Frontline",
    "url": "https://myanimelist.net/anime/46604/Dolls_Frontline",
    "total": 12,
    "image": "https://cdn.myanimelist.net/images/anime/1783/118956.jpg",
    "anidbId": 16006,
    "Sites": {
        "Gogoanime": {
            "dolls-frontline": {
                "id": 39723,
                "identifier": "dolls-frontline",
                "image": "https://gogocdn.net/cover/dolls-frontline.png",
                "malId": 46604,
                "aniId": 128828,
                "page": "Gogoanime",
                "title": "Dolls' Frontline",
                "type": "anime",
                "url": "https://anitaku.bz/category/dolls-frontline"
            },
            "dolls-frontline-dub": {
                "id": 40241,
                "identifier": "dolls-frontline-dub",
                "image": "https://gogocdn.net/cover/dolls-frontline-dub.png",
                "malId": 46604,
                "aniId": 128828,
                "page": "Gogoanime",
                "title": "Dolls' Frontline (Dub)",
                "type": "anime",
                "url": "https://anitaku.bz/category/dolls-frontline-dub"
            }
        },
        "Zoro": {
            "17518": {
                "id": 50047,
                "identifier": "17518",
                "image": "https://cdn.noitatnemucod.net/thumbnail/300x400/100/a99dfa563332e3ed8f4e14f04137a7ff.png",
                "malId": 46604,
                "aniId": 128828,
                "page": "Zoro",
                "title": "Dolls' Frontline",
                "type": "anime",
                "url": "https://hianime.to/dolls-frontline-17518"
            }
        },
        "animepahe": {
            "4674": {
                "identifier": "4674",
                "malId": 46604,
                "type": "anime",
                "page": "animepahe",
                "title": "Girls' Frontline",
                "url": "https://animepahe.ru/a/4674",
                "aniId": 128828
            }
        },
        "Crunchyroll": {
            "0": {
                "title": "Dolls' Frontline",
                "image": "https://s4.anilist.co/file/anilistcdn/media/anime/cover/medium/bx128828-Lhulr8Niitey.png",
                "identifier": 0,
                "url": "https://www.crunchyroll.com/girls-frontline",
                "type": "anime",
                "page": "Crunchyroll",
                "external": true,
                "aniId": 128828
            }
        }
    },
    "malId": 46604
}