{
    "id": 1412,
    "type": "anime",
    "title": "Lupin III",
    "url": "https://myanimelist.net/anime/1412/Lupin_III",
    "total": 23,
    "image": "https://cdn.myanimelist.net/images/anime/10/15625.jpg",
    "anidbId": 421,
    "Sites": {
        "9anime": {
            "778": {
                "identifier": "778",
                "image": "https://static.bunnycdn.ru/i/cache/images/2018/04/faeb83a0b47adfd551dc565699766c51.jpg",
                "malId": 1412,
                "aniId": 1412,
                "page": "9anime",
                "title": "Lupin III",
                "type": "anime",
                "url": "https://aniwave.to/watch/lupin-the-3rd.778"
            },
            "4kyo": {
                "identifier": "4kyo",
                "image": "https://static.bunnycdn.ru/i/cache/images/f/f5/f57a5715ffa26b7b322fe55d68ce5159.jpg",
                "malId": 1412,
                "aniId": 1412,
                "page": "9anime",
                "title": "Lupin III: World's Most Wanted",
                "type": "anime",
                "url": "https://aniwave.to/watch/lupin-iii-worlds-most-wanted.4kyo"
            }
        },
        "Gogoanime": {
            "lupin-iii": {
                "identifier": "lupin-iii",
                "image": "https://gogocdn.net/images/anime/L/lupin-iii.jpg",
                "malId": 1412,
                "aniId": 1412,
                "page": "Gogoanime",
                "title": "Lupin III",
                "type": "anime",
                "url": "https://anitaku.to/category/lupin-iii"
            },
            "lupin-iii-dub": {
                "identifier": "lupin-iii-dub",
                "image": "https://gogocdn.net/cover/lupin-iii-dub.png",
                "malId": 1412,
                "aniId": 1412,
                "page": "Gogoanime",
                "title": "Lupin III (Dub)",
                "type": "anime",
                "url": "https://anitaku.to/category/lupin-iii-dub"
            }
        },
        "Zoro": {
            "1126": {
                "identifier": "1126",
                "image": "https://cdn.noitatnemucod.net/thumbnail/300x400/100/170a925f89b941a98f0be20ad3ea6e4a.jpg",
                "malId": 1412,
                "aniId": 1412,
                "page": "Zoro",
                "title": "Lupin III",
                "type": "anime",
                "url": "https://hianime.to/lupin-iii-1126"
            }
        },
        "animepahe": {
            "1778": {
                "identifier": "1778",
                "malId": 1412,
                "type": "anime",
                "page": "animepahe",
                "title": "Lupin III",
                "url": "https://animepahe.ru/a/1778",
                "aniId": 1412
            }
        },
        "YugenAnime": {
            "2081": {
                "identifier": "2081",
                "malId": 1412,
                "type": "anime",
                "page": "YugenAnime",
                "title": "Lupin III",
                "url": "https://yugenanime.tv/anime/2081/lupin-iii/",
                "aniId": 1412
            }
        },
        "Hulu": {
            "0": {
                "title": "Lupin III",
                "image": "https://s4.anilist.co/file/anilistcdn/media/anime/cover/medium/nx1412-70kA9bzDoleV.jpg",
                "identifier": 0,
                "url": "http://www.hulu.com/lupin-the-third-part-1",
                "type": "anime",
                "page": "Hulu",
                "external": true,
                "aniId": 1412
            }
        },
        "Crunchyroll": {
            "1": {
                "title": "Lupin III",
                "image": "https://s4.anilist.co/file/anilistcdn/media/anime/cover/medium/nx1412-70kA9bzDoleV.jpg",
                "identifier": 1,
                "url": "http://www.crunchyroll.com/lupin-the-third-part-1",
                "type": "anime",
                "page": "Crunchyroll",
                "external": true,
                "aniId": 1412
            }
        },
        "Hidive": {
            "2": {
                "title": "Lupin III",
                "image": "https://s4.anilist.co/file/anilistcdn/media/anime/cover/medium/nx1412-70kA9bzDoleV.jpg",
                "identifier": 2,
                "url": "https://www.hidive.com/tv/lupin-the-3rd-part-1",
                "type": "anime",
                "page": "Hidive",
                "external": true,
                "aniId": 1412
            }
        }
    },
    "malId": 1412
}