{
    "id": 1968,
    "type": "anime",
    "title": "Kidou Senshi Z Gundam II: Koibito-tachi",
    "url": "https://myanimelist.net/anime/1968/Kidou_Senshi_Z_Gundam_II__Koibito-tachi",
    "total": 1,
    "image": "https://cdn.myanimelist.net/images/anime/1183/94730.jpg",
    "anidbId": 3969,
    "Sites": {
        "Gogoanime": {
            "mobile-suit-zeta-gundam-a-new-translation-ii-lovers": {
                "identifier": "mobile-suit-zeta-gundam-a-new-translation-ii-lovers",
                "image": "https://gogocdn.net/cover/mobile-suit-zeta-gundam-a-new-translation-ii-lovers.png",
                "malId": 1968,
                "aniId": 1968,
                "page": "Gogoanime",
                "title": "Mobile Suit Zeta Gundam: A New Translation II - Lovers",
                "type": "anime",
                "url": "https://anitaku.bz/category/mobile-suit-zeta-gundam-a-new-translation-ii-lovers"
            }
        },
        "animepahe": {
            "3569": {
                "identifier": "3569",
                "malId": 1968,
                "type": "anime",
                "page": "animepahe",
                "title": "Mobile Suit Zeta Gundam: A New Translation II - Lovers",
                "url": "https://animepahe.ru/a/3569",
                "aniId": 1968
            }
        }
    },
    "malId": 1968
}