{
    "id": 4476,
    "type": "anime",
    "title": "Gensoumaden Saiyuuki: Kibou no Zaika",
    "url": "https://myanimelist.net/anime/4476/Gensoumaden_Saiyuuki__Kibou_no_Zaika",
    "total": 1,
    "image": "https://cdn.myanimelist.net/images/anime/11/8575.jpg",
    "anidbId": 4973,
    "Sites": {
        "9anime": {
            "7zpj": {
                "identifier": "7zpj",
                "image": "https://static.bunnycdn.ru/i/cache/images/2018/04/362f5050cbba6c9916f1893c50dbe471.jpg",
                "malId": 4476,
                "aniId": 4476,
                "page": "9anime",
                "title": "Saiyuuki Interactive OVA",
                "type": "anime",
                "url": "https://aniwave.to/watch/saiyuki-interactive.7zpj"
            }
        },
        "Zoro": {
            "3647": {
                "identifier": "3647",
                "image": "https://img.flawlessfiles.com/_r/300x400/100/d9/88/d988f3a086caf802fbddfd74dbc4c307/d988f3a086caf802fbddfd74dbc4c307.jpg",
                "malId": 4476,
                "aniId": 4476,
                "page": "Zoro",
                "title": "Saiyuki Interactive",
                "type": "anime",
                "url": "https://aniwatch.to/saiyuki-interactive-3647"
            }
        }
    },
    "malId": 4476
}