{
    "id": 5031,
    "type": "anime",
    "title": "Cobra The Animation: Time Drive",
    "url": "https://myanimelist.net/anime/5031/Cobra_The_Animation__Time_Drive",
    "total": 2,
    "image": "https://cdn.myanimelist.net/images/anime/11/14093.jpg",
    "anidbId": 6392,
    "Sites": {
        "9anime": {
            "zw7l": {
                "identifier": "zw7l",
                "image": "https://static.aniwave.to/i/2018/04/b2e21d73295bffb6d62b82aae8e7eac5.jpg",
                "malId": 5031,
                "aniId": 5031,
                "page": "9anime",
                "title": "COBRA THE ANIMATION: Time Drive",
                "type": "anime",
                "url": "https://aniwave.to/watch/cobra-time-drive.zw7l"
            }
        },
        "Gogoanime": {
            "cobra-the-animation-time-drive-ova": {
                "identifier": "cobra-the-animation-time-drive-ova",
                "image": "https://gogocdn.net/images/anime/C/21988.jpg",
                "malId": 5031,
                "aniId": 5031,
                "page": "Gogoanime",
                "title": "Cobra The Animation: Time Drive (OVA)",
                "type": "anime",
                "url": "https://anitaku.pe/category/cobra-the-animation-time-drive-ova"
            }
        },
        "Zoro": {
            "3813": {
                "identifier": "3813",
                "image": "https://cdn.noitatnemucod.net/thumbnail/300x400/100/71ff7ffe164342a091e2a0f9eb2818e0.jpg",
                "malId": 5031,
                "aniId": 5031,
                "page": "Zoro",
                "title": "Cobra The Animation: Time Drive",
                "type": "anime",
                "url": "https://hianime.to/cobra-the-animation-time-drive-3813"
            }
        },
        "YugenAnime": {
            "5742": {
                "identifier": "5742",
                "malId": 5031,
                "type": "anime",
                "page": "YugenAnime",
                "title": "Cobra The Animation: Time Drive",
                "url": "https://yugenanime.tv/anime/5742/cobra-the-animation-time-drive-ova/",
                "aniId": 5031
            }
        },
        "Hidive": {
            "0": {
                "title": "COBRA THE ANIMATION: Time Drive",
                "image": "https://s4.anilist.co/file/anilistcdn/media/anime/cover/medium/5031.jpg",
                "identifier": 0,
                "url": "https://www.hidive.com/movies/cobra-time-drive",
                "type": "anime",
                "page": "Hidive",
                "external": true,
                "aniId": 5031
            }
        }
    },
    "malId": 5031
}