{
    "id": 9863,
    "type": "anime",
    "title": "SKET Dance",
    "url": "https://myanimelist.net/anime/9863/SKET_Dance",
    "total": 77,
    "image": "https://cdn.myanimelist.net/images/anime/9/73974.jpg",
    "anidbId": 8039,
    "Sites": {
        "Zoro": {
            "243": {
                "id": 51317,
                "identifier": "243",
                "image": "https://cdn.noitatnemucod.net/thumbnail/300x400/100/fb1513537e7bf8412f273aa2e123926a.jpg",
                "malId": 9863,
                "aniId": 9863,
                "page": "Zoro",
                "title": "SKET Dance",
                "type": "anime",
                "url": "https://hianimez.to/sket-dance-243"
            }
        },
        "animepahe": {
            "747": {
                "identifier": "747",
                "malId": 9863,
                "type": "anime",
                "page": "animepahe",
                "title": "SKET Dance",
                "url": "https://animepahe.ru/a/747",
                "aniId": 9863
            }
        },
        "Crunchyroll": {
            "0": {
                "title": "SKET DANCE",
                "image": "https://s4.anilist.co/file/anilistcdn/media/anime/cover/medium/bx9863-G6dAvTVsfLRO.png",
                "identifier": 0,
                "url": "http://www.crunchyroll.com/sket-dance",
                "type": "anime",
                "page": "Crunchyroll",
                "external": true,
                "aniId": 9863
            }
        }
    },
    "malId": 9863
}