{
    "id": 108,
    "type": "manga",
    "title": "Gouhou Drug",
    "url": "https://myanimelist.net/manga/108/Gouhou_Drug",
    "total": 18,
    "image": "https://cdn.myanimelist.net/images/manga/1/185400.jpg",
    "Sites": {
        "Mangadex": {
            "8b530af3-b431-48ff-8d37-32b304765503": {
                "identifier": "8b530af3-b431-48ff-8d37-32b304765503",
                "image": "https://uploads.mangadex.org/covers/8b530af3-b431-48ff-8d37-32b304765503/d5992df2-9dc7-4d13-be4a-a5ec82271d94.jpg",
                "malId": 108,
                "aniId": 30108,
                "page": "Mangadex",
                "title": "Gohou Drug",
                "type": "manga",
                "url": "https://mangadex.org/title/8b530af3-b431-48ff-8d37-32b304765503"
            }
        },
        "MangaSee": {
            "gohou-drug": {
                "identifier": "gohou-drug",
                "image": "https://temp.compsci88.com/cover/Gohou-Drug.jpg",
                "malId": 108,
                "aniId": 30108,
                "page": "MangaSee",
                "title": "Legal Drug",
                "type": "manga",
                "url": "https://mangasee123.com/manga/Gohou-Drug"
            }
        },
        "MangaFire": {
            "gohou-drug.r4kn": {
                "identifier": "gohou-drug.r4kn",
                "image": "https://static.mangafire.to/3b2d5/i/9/9f/9f557d8619a5871c12faa38245ca194b.jpg",
                "malId": 108,
                "aniId": 30108,
                "page": "MangaFire",
                "title": "Legal Drug",
                "type": "manga",
                "url": "https://mangafire.to/manga/gohou-drug.r4kn/"
            }
        },
        "MangaNato": {
            "manga-au978329": {
                "identifier": "manga-au978329",
                "image": "https://avt.mkklcdnv6temp.com/fld/56/g/8-1732790340-nw.webp",
                "malId": 108,
                "aniId": 30108,
                "page": "MangaNato",
                "title": "Legal Drug",
                "type": "manga",
                "url": "https://manganato.com/manga-au978329"
            }
        },
        "Weebcentral": {
            "01j76xy9st6wj7mtd7pxv7khan": {
                "identifier": "01j76xy9st6wj7mtd7pxv7khan",
                "image": "https://temp.compsci88.com/cover/fallback/01J76XY9ST6WJ7MTD7PXV7KHAN.jpg",
                "malId": 108,
                "aniId": 30108,
                "page": "Weebcentral",
                "title": "Legal Drug",
                "type": "manga",
                "url": "https://weebcentral.com/series/01J76XY9ST6WJ7MTD7PXV7KHAN"
            }
        },
        "Comick": {
            "S08fA65p": {
                "identifier": "S08fA65p",
                "malId": 108,
                "type": "manga",
                "page": "Comick",
                "title": "Gohou Drug",
                "url": "https://comick.io/comic/gohou-drug",
                "aniId": 30108
            }
        }
    },
    "aniId": 30108
}