{
    "id": 10826,
    "type": "manga",
    "title": "Yuurei Ryokoudairiten",
    "url": "https://myanimelist.net/manga/10826/Yuurei_Ryokoudairiten",
    "total": 23,
    "image": "https://cdn.myanimelist.net/images/manga/1/14572.jpg",
    "Sites": {
        "Mangadex": {
            "13f5054b-045d-48fe-bc5b-fe146c4c9733": {
                "identifier": "13f5054b-045d-48fe-bc5b-fe146c4c9733",
                "image": "https://uploads.mangadex.org/covers/13f5054b-045d-48fe-bc5b-fe146c4c9733/c4cb31e1-3a2a-485d-9bf8-79c6a9c9ca90.jpg",
                "malId": 10826,
                "aniId": 40826,
                "page": "Mangadex",
                "title": "Yuurei Ryokou Dairiten - Soul Mate Tourist",
                "type": "manga",
                "url": "https://mangadex.org/title/13f5054b-045d-48fe-bc5b-fe146c4c9733"
            }
        },
        "MangaFire": {
            "yuurei-ryokou-dairiten-soul-mate-tourist.xnkq": {
                "identifier": "yuurei-ryokou-dairiten-soul-mate-tourist.xnkq",
                "image": "https://static.mangafire.to/i/1/17/17a4ae95740f8f7c8b3e09332b8068c2.jpg",
                "malId": 10826,
                "aniId": 40826,
                "page": "MangaFire",
                "title": "Soul Mate Tourist",
                "type": "manga",
                "url": "https://mangafire.to/manga/yuurei-ryokou-dairiten-soul-mate-tourist.xnkq/"
            }
        },
        "Comick": {
            "Rm1vjpHV": {
                "identifier": "Rm1vjpHV",
                "malId": 10826,
                "type": "manga",
                "page": "Comick",
                "title": "Yuurei Ryokou Dairiten - Soul Mate Tourist",
                "url": "https://comick.io/comic/yuurei-ryokou-dairiten-soul-mate-tourist",
                "aniId": 40826
            }
        }
    },
    "aniId": 40826
}