{
    "id": 109048,
    "type": "manga",
    "title": "Yasuraka Monsters",
    "url": "https://myanimelist.net/manga/109048/Yasuraka_Monsters",
    "image": "https://cdn.myanimelist.net/images/manga/2/204845.jpg",
    "Sites": {
        "Mangadex": {
            "27020aad-ab31-4792-9a5c-26658b23c012": {
                "identifier": "27020aad-ab31-4792-9a5c-26658b23c012",
                "image": "https://uploads.mangadex.org/covers/27020aad-ab31-4792-9a5c-26658b23c012/f789a9d2-4769-4931-9794-f3fa37786927.jpg",
                "malId": 109048,
                "aniId": 113442,
                "page": "Mangadex",
                "title": "Yasuraka Monsters",
                "type": "manga",
                "url": "https://mangadex.org/title/27020aad-ab31-4792-9a5c-26658b23c012"
            }
        },
        "Comick": {
            "0_bqq9EC": {
                "identifier": "0_bqq9EC",
                "malId": 109048,
                "type": "manga",
                "page": "Comick",
                "title": "Yasuraka Monsters",
                "url": "https://comick.app/comic/yasuraka-monsters",
                "aniId": 113442
            }
        },
        "MangaReader": {
            "23477": {
                "identifier": "23477",
                "malId": 109048,
                "type": "manga",
                "page": "MangaReader",
                "title": "Yasuraka Monsters",
                "url": "https://mangareader.to/hella-chill-monsters-23477",
                "aniId": 113442
            }
        }
    },
    "aniId": 113442
}