{
    "id": 109746,
    "type": "manga",
    "title": "Hito no Ko",
    "url": "https://myanimelist.net/manga/109746/Hito_no_Ko",
    "total": null,
    "image": "https://cdn.myanimelist.net/images/manga/2/207634.jpg",
    "Sites": {
        "Mangadex": {
            "801626b1-8a28-4870-b12a-8dc58e7ee738": {
                "identifier": "801626b1-8a28-4870-b12a-8dc58e7ee738",
                "image": "https://uploads.mangadex.org/covers/801626b1-8a28-4870-b12a-8dc58e7ee738/489e19a7-73d4-4b63-ad32-865f249a52ed.png",
                "malId": 109746,
                "aniId": 100351,
                "page": "Mangadex",
                "title": "Human Powder",
                "type": "manga",
                "url": "https://mangadex.org/title/801626b1-8a28-4870-b12a-8dc58e7ee738"
            }
        },
        "Comick": {
            "911uUhuj": {
                "identifier": "911uUhuj",
                "malId": 109746,
                "type": "manga",
                "page": "Comick",
                "title": "Human Powder",
                "url": "https://comick.io/comic/human-powder",
                "aniId": 100351
            }
        }
    },
    "aniId": 100351
}