{
    "id": 127930,
    "type": "manga",
    "title": "Kusattemo Ani.",
    "url": "https://myanimelist.net/manga/127930/Kusattemo_Ani",
    "image": "https://cdn.myanimelist.net/images/manga/2/236433.jpg",
    "Sites": {
        "Mangadex": {
            "b04fa4cc-8b14-4ffa-bcad-1275657af471": {
                "identifier": "b04fa4cc-8b14-4ffa-bcad-1275657af471",
                "image": "https://uploads.mangadex.org/covers/b04fa4cc-8b14-4ffa-bcad-1275657af471/c67ff267-5d49-4e3b-9998-70088c4e3bad.jpg",
                "malId": 127930,
                "aniId": 116590,
                "page": "Mangadex",
                "title": "Kusatte mo Ani.",
                "type": "manga",
                "url": "https://mangadex.org/title/b04fa4cc-8b14-4ffa-bcad-1275657af471"
            }
        }
    },
    "aniId": 116590
}