{
    "id": 136720,
    "type": "manga",
    "title": "Puchi Love★Kingdom",
    "url": "https://myanimelist.net/manga/136720/Puchi_Love★Kingdom",
    "total": 9,
    "image": "https://cdn.myanimelist.net/images/manga/3/244831.jpg",
    "Sites": {
        "Mangadex": {
            "9fdad913-0726-4011-860d-55b6e52cb385": {
                "identifier": "9fdad913-0726-4011-860d-55b6e52cb385",
                "image": "https://uploads.mangadex.org/covers/9fdad913-0726-4011-860d-55b6e52cb385/70d0e1a6-c444-477e-867b-cf1c88dd290d.jpg",
                "malId": 136720,
                "aniId": 119293,
                "page": "Mangadex",
                "title": "Puchi Love Kingdom",
                "type": "manga",
                "url": "https://mangadex.org/title/9fdad913-0726-4011-860d-55b6e52cb385"
            }
        },
        "Comick": {
            "PtVSqkuw": {
                "identifier": "PtVSqkuw",
                "malId": 136720,
                "type": "manga",
                "page": "Comick",
                "title": "Puchi Love Kingdom",
                "url": "https://comick.io/comic/puchi-love-kingdom",
                "aniId": 119293
            }
        }
    },
    "aniId": 119293
}