{
    "id": 141874,
    "type": "manga",
    "title": "Strange Moon",
    "url": "https://myanimelist.net/manga/141874/Strange_Moon",
    "total": null,
    "image": "https://cdn.myanimelist.net/images/manga/3/252460.jpg",
    "Sites": {
        "Mangadex": {
            "77a95107-bbf5-4f8a-8094-68982894a7b7": {
                "id": 124913,
                "identifier": "77a95107-bbf5-4f8a-8094-68982894a7b7",
                "image": "https://uploads.mangadex.org/covers/77a95107-bbf5-4f8a-8094-68982894a7b7/6added01-b7e3-45ed-9f3d-d39aef4185da.jpg",
                "malId": 141874,
                "aniId": 129670,
                "page": "Mangadex",
                "title": "Strange Moon",
                "type": "manga",
                "url": "https://mangadex.org/title/77a95107-bbf5-4f8a-8094-68982894a7b7"
            }
        }
    },
    "aniId": 129670
}