{
    "id": 25610,
    "type": "manga",
    "title": "C-",
    "url": "https://myanimelist.net/manga/25610/C-",
    "total": 10,
    "image": "https://cdn.myanimelist.net/images/manga/2/41208.jpg",
    "Sites": {
        "Mangadex": {
            "602d05c5-1893-4c4b-92ab-83293e6bfa1a": {
                "id": 28316,
                "identifier": "602d05c5-1893-4c4b-92ab-83293e6bfa1a",
                "image": "https://uploads.mangadex.org/covers/602d05c5-1893-4c4b-92ab-83293e6bfa1a/67139bd3-93e7-4ae6-ab95-80b2ab03573a.jpg",
                "malId": 25610,
                "aniId": 55610,
                "page": "Mangadex",
                "title": "Kurosaki Rendou Sakuhinshuu",
                "type": "manga",
                "url": "https://mangadex.org/title/602d05c5-1893-4c4b-92ab-83293e6bfa1a"
            }
        }
    },
    "aniId": 55610
}