{
    "id": 48573,
    "type": "manga",
    "title": "Rose Guns Days: Fukushuu wa Ougon no Kaori",
    "url": "https://myanimelist.net/manga/48573/Rose_Guns_Days__Fukushuu_wa_Ougon_no_Kaori",
    "total": 12,
    "image": "https://cdn.myanimelist.net/images/manga/1/115979.jpg",
    "Sites": {
        "Mangadex": {
            "3aae0e61-7509-491d-947b-9a3659dbea4c": {
                "id": 12781,
                "identifier": "3aae0e61-7509-491d-947b-9a3659dbea4c",
                "image": "https://uploads.mangadex.org/covers/3aae0e61-7509-491d-947b-9a3659dbea4c/73a96969-77be-4b58-89c0-5b90169b893f.jpg",
                "malId": 48573,
                "aniId": 78573,
                "page": "Mangadex",
                "title": "Rose Guns Days - Fukushuu wa Ougon no Kaori",
                "type": "manga",
                "url": "https://mangadex.org/title/3aae0e61-7509-491d-947b-9a3659dbea4c"
            }
        },
        "Comick": {
            "oYOQWeNp": {
                "identifier": "oYOQWeNp",
                "malId": 48573,
                "type": "manga",
                "page": "Comick",
                "title": "Rose Guns Days - Fukushuu wa Ougon no Kaori",
                "url": "https://comick.io/comic/rose-guns-days-fukushuu-wa-ougon-no-kaori",
                "aniId": 78573
            }
        }
    },
    "aniId": 78573
}