{
    "id": 59191,
    "type": "manga",
    "title": "Sayonara Sorcier",
    "url": "https://myanimelist.net/manga/59191/Sayonara_Sorcier",
    "total": 12,
    "image": "https://cdn.myanimelist.net/images/manga/1/314492.jpg",
    "Sites": {
        "Mangadex": {
            "d0d2388c-3cb2-4286-8d73-9e509c5b324b": {
                "identifier": "d0d2388c-3cb2-4286-8d73-9e509c5b324b",
                "image": "https://uploads.mangadex.org/covers/d0d2388c-3cb2-4286-8d73-9e509c5b324b/b1515a51-3736-4de7-8f53-543d3d3cd55b.jpg",
                "malId": 59191,
                "aniId": 86818,
                "page": "Mangadex",
                "title": "Sayonara Sorcier",
                "type": "manga",
                "url": "https://mangadex.org/title/d0d2388c-3cb2-4286-8d73-9e509c5b324b"
            }
        },
        "MangaFox": {
            "sayonara_sorcier": {
                "identifier": "sayonara_sorcier",
                "image": "https://fmcdn.mfcdn.net/store/manga/13666/cover.jpg",
                "malId": 59191,
                "aniId": 86818,
                "page": "MangaFox",
                "title": "Sayonara Sorcier",
                "type": "manga",
                "url": "https://fanfox.net/manga/sayonara_sorcier/"
            }
        },
        "MangaFire": {
            "sayonara-sorcier.0zk3": {
                "identifier": "sayonara-sorcier.0zk3",
                "image": "https://static.mangafire.to/3b2d5/i/d/d1/d1b8f8b964372a4c6fb5a1cf873696f8.jpg",
                "malId": 59191,
                "aniId": 86818,
                "page": "MangaFire",
                "title": "Sayonara Sorcier",
                "type": "manga",
                "url": "https://mangafire.to/manga/sayonara-sorcier.0zk3/"
            }
        },
        "Comick": {
            "lwiOZKp0": {
                "identifier": "lwiOZKp0",
                "malId": 59191,
                "type": "manga",
                "page": "Comick",
                "title": "Sayonara Sorcier",
                "url": "https://comick.io/comic/sayonara-sorcier",
                "aniId": 86818
            }
        }
    },
    "aniId": 86818
}