{
    "id": 18071,
    "type": "anime",
    "title": "Chalk-iro no People",
    "url": "https://myanimelist.net/anime/18071/Chalk-iro_no_People",
    "total": 1,
    "image": "https://cdn.myanimelist.net/images/anime/11/48001.jpg",
    "anidbId": 6810,
    "Sites": {
        "9anime": {
            "3rvx6": {
                "identifier": "3rvx6",
                "image": "https://static.aniwave.to/i/e/ea/4af996ae884299ed0a2d7cebd5ea9c6a.jpg",
                "malId": 18071,
                "aniId": 18071,
                "page": "9anime",
                "title": "Chalk-iro no People",
                "type": "anime",
                "url": "https://aniwave.to/watch/chalk-iro-no-people.3rvx6"
            }
        }
    },
    "aniId": 18071
}