{
    "id": 19587,
    "type": "anime",
    "title": "Kaiketsu Zorori: Mamoru ze! Kyouryuu no Tamago",
    "url": "https://myanimelist.net/anime/19587/Kaiketsu_Zorori__Mamoru_ze_Kyouryuu_no_Tamago",
    "total": null,
    "image": "https://cdn.myanimelist.net/images/anime/10/52451.jpg",
    "anidbId": 9970,
    "Sites": {
        "9anime": {
            "7r88": {
                "identifier": "7r88",
                "image": "https://static.bunnycdn.ru/i/cache/images/2018/07/8de04c098877fce13de32d68d1b5ab35.jpg",
                "malId": 19587,
                "aniId": 19587,
                "page": "9anime",
                "title": "Kaiketsu Zorori: Mamoru ze! Kyouryuu no Tamago",
                "type": "anime",
                "url": "https://aniwave.to/watch/kaiketsu-zorori-mamoru-ze-kyouryuu-no-tamago.7r88"
            }
        },
        "YugenAnime": {
            "5002": {
                "identifier": "5002",
                "malId": 19587,
                "type": "anime",
                "page": "YugenAnime",
                "title": "Kaiketsu Zorori: Mamoru ze! Kyouryuu no Tamago",
                "url": "https://yugenanime.tv/anime/5002/kaiketsu-zorori-mamoru-ze-kyouryuu-no-tamago/",
                "aniId": 19587
            }
        }
    },
    "aniId": 19587
}