{
    "id": 20127,
    "type": "anime",
    "title": "Kariage-kun",
    "url": "https://myanimelist.net/anime/20127/Kariage-kun",
    "total": 59,
    "image": "https://cdn.myanimelist.net/images/anime/1686/142951.jpg",
    "anidbId": 2083,
    "Sites": {
        "Zoro": {
            "14528": {
                "id": 53317,
                "identifier": "14528",
                "image": "https://cdn.noitatnemucod.net/thumbnail/300x400/100/24e4ce404c888955631ebcb0b395bbd2.jpg",
                "malId": 20127,
                "aniId": 20127,
                "page": "Zoro",
                "title": "Kariage-kun",
                "type": "anime",
                "url": "https://hianimez.to/kariage-kun-14528"
            }
        }
    },
    "aniId": 20127
}