{
    "id": 21487,
    "type": "anime",
    "title": "Shin Dokonjou Gaeru",
    "url": "https://myanimelist.net/anime/21487/Shin_Dokonjou_Gaeru",
    "total": 30,
    "image": "https://cdn.myanimelist.net/images/anime/8/56689.jpg",
    "anidbId": 4954,
    "Sites": {
        "Zoro": {
            "11551": {
                "identifier": "11551",
                "image": "https://cdn.noitatnemucod.net/thumbnail/300x400/100/a99cc3981d76bc0ff470ba578764a5e1.jpg",
                "malId": 21487,
                "aniId": 126865,
                "page": "Zoro",
                "title": "[RAW] Shin Dokonjou Gaeru",
                "type": "anime",
                "url": "https://hianime.to/raw-shin-dokonjou-gaeru-11551"
            }
        }
    },
    "aniId": 126865
}