{
    "id": 2543,
    "type": "anime",
    "title": "Robin Hood no Daibouken",
    "url": "https://myanimelist.net/anime/2543/Robin_Hood_no_Daibouken",
    "image": "https://cdn.myanimelist.net/images/anime/1755/97970.jpg",
    "anidbId": 1060,
    "Sites": {
        "9anime": {
            "w7jk": {
                "identifier": "w7jk",
                "image": "https://img.aniwave.to/i/cache/images/2018/08/a80dff1d90d40234bd6a25799c412b3f.jpg",
                "malId": 2543,
                "aniId": 2543,
                "page": "9anime",
                "title": "Robin Hood no Daibouken",
                "type": "anime",
                "url": "https://aniwave.to/watch/the-great-adventures-of-robin-hood.w7jk"
            },
            "ojxo4": {
                "identifier": "ojxo4",
                "image": "https://img.aniwave.to/i/cache/images/1/1e/1edb2d57cccdee7901803a491aa17ae7.jpg",
                "malId": 2543,
                "aniId": 2543,
                "page": "9anime",
                "title": "Robin Hood II & The Invincible Knight",
                "type": "anime",
                "url": "https://aniwave.to/watch/robin-hood-ii-the-invincible-knight-dub.ojxo4"
            }
        },
        "Gogoanime": {
            "robin-hood-no-daibouken": {
                "identifier": "robin-hood-no-daibouken",
                "image": "https://gogocdn.net/cover/robin-hood-no-daibouken.png",
                "malId": 2543,
                "aniId": 2543,
                "page": "Gogoanime",
                "title": "Robin Hood no Daibouken",
                "type": "anime",
                "url": "https://anitaku.to/category/robin-hood-no-daibouken"
            }
        },
        "YugenAnime": {
            "4725": {
                "identifier": "4725",
                "malId": 2543,
                "type": "anime",
                "page": "YugenAnime",
                "title": "Robin Hood no Daibouken",
                "url": "https://yugenanime.tv/anime/4725/robin-hood-no-daibouken/",
                "aniId": 2543
            }
        }
    },
    "aniId": 2543
}