{
    "id": 2563,
    "type": "anime",
    "title": "Aria the OVA: Arietta",
    "url": "https://myanimelist.net/anime/2563/Aria_the_OVA__Arietta",
    "total": 1,
    "image": "https://cdn.myanimelist.net/images/anime/11/77622.jpg",
    "anidbId": 5115,
    "Sites": {
        "Zoro": {
            "483": {
                "id": 47461,
                "identifier": "483",
                "image": "https://cdn.noitatnemucod.net/thumbnail/300x400/100/41f0760002b748337ba33f6fda9d7ad3.jpg",
                "malId": 2563,
                "aniId": 2563,
                "page": "Zoro",
                "title": "Aria the OVA: Arietta",
                "type": "anime",
                "url": "https://hianimez.to/aria-the-ova-arietta-483"
            }
        },
        "animepahe": {
            "2171": {
                "identifier": "2171",
                "malId": 2563,
                "type": "anime",
                "page": "animepahe",
                "title": "Aria the OVA: Arietta",
                "url": "https://animepahe.ru/a/2171",
                "aniId": 2563
            }
        }
    },
    "aniId": 2563
}