{
    "id": 3493,
    "type": "anime",
    "title": "Ryuusei no Rockman Tribe",
    "url": "https://myanimelist.net/anime/3493/Ryuusei_no_Rockman_Tribe",
    "total": 21,
    "image": "https://cdn.myanimelist.net/images/anime/1256/94652.jpg",
    "anidbId": 5524,
    "Sites": {
        "Gogoanime": {
            "ryuusei-no-rockman-tribe": {
                "identifier": "ryuusei-no-rockman-tribe",
                "image": "https://gogocdn.net/cover/ryuusei-no-rockman-tribe.png",
                "malId": 3493,
                "aniId": 3493,
                "page": "Gogoanime",
                "title": "Ryuusei no Rockman Tribe",
                "type": "anime",
                "url": "https://anitaku.bz/category/ryuusei-no-rockman-tribe"
            }
        },
        "Zoro": {
            "3620": {
                "identifier": "3620",
                "image": "https://cdn.noitatnemucod.net/thumbnail/300x400/100/c9b1c804bc0f5342af29335a3d907c02.jpg",
                "malId": 3493,
                "aniId": 3493,
                "page": "Zoro",
                "title": "Mega Man Star Force Tribe",
                "type": "anime",
                "url": "https://hianime.to/mega-man-star-force-tribe-3620"
            }
        }
    },
    "aniId": 3493
}