{
    "id": 4485,
    "type": "anime",
    "title": "Kasei Yakyoku",
    "url": "https://myanimelist.net/anime/4485/Kasei_Yakyoku",
    "total": 4,
    "image": "https://cdn.myanimelist.net/images/anime/4/50129.jpg",
    "anidbId": 2606,
    "Sites": {
        "Gogoanime": {
            "kasei-yakyoku": {
                "id": 40217,
                "identifier": "kasei-yakyoku",
                "image": "https://gogocdn.net/cover/kasei-yakyoku.png",
                "malId": 4485,
                "aniId": 4485,
                "page": "Gogoanime",
                "title": "Kasei Yakyoku",
                "type": "anime",
                "url": "https://anitaku.bz/category/kasei-yakyoku"
            }
        },
        "Zoro": {
            "4898": {
                "id": 73039,
                "identifier": "4898",
                "image": "https://cdn.noitatnemucod.net/thumbnail/300x400/100/4585bf6f8e13f375a033af00f3ab4951.jpg",
                "malId": 4485,
                "aniId": 4485,
                "page": "Zoro",
                "title": "Nightsong of Splendor",
                "type": "anime",
                "url": "https://hianime.to/nightsong-of-splendor-4898"
            }
        }
    },
    "aniId": 4485
}