{
    "id": 57097,
    "type": "anime",
    "title": "Wanneng Lian Ai Zahuo Dian",
    "url": "https://myanimelist.net/anime/57097/Wanneng_Lian_Ai_Zahuo_Dian",
    "total": 16,
    "image": "https://cdn.myanimelist.net/images/anime/1223/139544.jpg",
    "anidbId": null,
    "Sites": {
        "Gogoanime": {
            "love-magic-grovery": {
                "id": 54331,
                "identifier": "love-magic-grovery",
                "image": "https://gogocdn.net/cover/love-magic-grovery.png",
                "malId": 57097,
                "aniId": 166455,
                "page": "Gogoanime",
                "title": "Love Magic Grovery",
                "type": "anime",
                "url": "https://anitaku.bz/category/love-magic-grovery"
            }
        },
        "Zoro": {
            "19519": {
                "id": 74509,
                "identifier": "19519",
                "image": "https://cdn.noitatnemucod.net/thumbnail/300x400/100/bbe7d9446f443410a55d0ffcbff4d8fd.jpg",
                "malId": 57097,
                "aniId": 166455,
                "page": "Zoro",
                "title": "Love Magic Grocery",
                "type": "anime",
                "url": "https://hianime.to/love-magic-grocery-19519"
            }
        }
    },
    "aniId": 166455
}